listo/__init__.py
listo/main.py
listo-0.7.0.dist-info/licenses/LICENSE.md
listo-0.7.0.dist-info/METADATA
listo-0.7.0.dist-info/WHEEL
listo-0.7.0.dist-info/top_level.txt
listo-0.7.0.dist-info/RECORD
