Metadata-Version: 2.4
Name: listo
Version: 0.7.0
Summary: An improved version of the List built-in
Author-email: Daniel Roy Greenfeld <daniel@feldroy.com>, "Audrey M. Roy Greenfeld" <audrey@feldroy.com>
Maintainer-email: Daniel Roy Greenfeld <daniel@feldroy.com>, "Audrey M. Roy Greenfeld" <audrey@feldroy.com>
License: MIT
Project-URL: bugs, https://github.com/pydanny/listo/issues
Project-URL: changelog, https://github.com/pydanny/listo/blob/master/CHANGELOG.md
Project-URL: homepage, https://github.com/pydanny/listo
Classifier: Development Status :: 5 - Production/Stable
Classifier: Intended Audience :: Developers
Classifier: License :: OSI Approved :: MIT License
Classifier: Programming Language :: Python :: 3.10
Classifier: Programming Language :: Python :: 3.11
Classifier: Programming Language :: Python :: 3.12
Classifier: Programming Language :: Python :: 3.13
Requires-Python: >=3.10
License-File: LICENSE.md
Provides-Extra: test
Requires-Dist: coverage; extra == "test"
Requires-Dist: pytest; extra == "test"
Requires-Dist: ruff; extra == "test"
Requires-Dist: ty; extra == "test"
Dynamic: license-file
